MANIFEST.in
README.rst
setup.py
bin/gaet
gaet/__init__.py
gaet/errors.yml
gaet/functional.py
gaet/gene.py
gaet/gene_types.yml
gaet/gff.py
gaet/main.py
gaet/types.py
gaet/util.py
gaet/version.py
gaet.egg-info/PKG-INFO
gaet.egg-info/SOURCES.txt
gaet.egg-info/dependency_links.txt
gaet.egg-info/requires.txt
gaet.egg-info/top_level.txt
gaet/metrics/__init__.py
gaet/metrics/count.py
gaet/metrics/distance.py
gaet/metrics/membership.py
gaet/metrics/size.py
gaet/metrics/util.py
requirements/default.txt