Metadata-Version: 1.1
Name: gaet
Version: 0.3.0
Summary: Evaluate the quality of a genome assembly based on annotated genes
Home-page: https://gitlab.com/michaelbarton/gaet/
Author: Michael Barton
Author-email: mail@michaelbarton.me.uk
License: BSD
Keywords: genomics bioinformatics sequencing assembly
Platform: UNKNOWN
Classifier: License :: OSI Approved :: BSD License
Classifier: Intended Audience :: Science/Research
Classifier: Natural Language :: English
Classifier: Operating System :: POSIX
Classifier: Programming Language :: Python :: 3.5
Classifier: Topic :: Scientific/Engineering :: Bio-Informatics
